{
  "_class": "symbolMaster",
  "backgroundColor": {
    "_class": "color",
    "alpha": 1,
    "blue": 1,
    "do_objectID": "F8ABD9E1-E021-41D7-9DE8-56BBB5C3BAA1",
    "green": 1,
    "red": 1
  },
  "booleanOperation": -1,
  "changeIdentifier": 330,
  "clippingMaskMode": 0,
  "do_objectID": "3C2BDC14-1C9A-4042-B6C6-F82A2A849091",
  "exportOptions": {
    "_class": "exportOptions",
    "do_objectID": "DDEB694E-8D96-42D4-9DE4-266F7903F70F",
    "exportFormats": [
    ],
    "includedLayerIds": [
    ],
    "layerOptions": 0,
    "shouldTrim": false
  },
  "frame": {
    "_class": "rect",
    "constrainProportions": false,
    "do_objectID": "2E69DB62-6301-4EA0-AF10-6BE08285BA7B",
    "height": 28,
    "width": 97,
    "x": 5322,
    "y": -60
  },
  "hasBackgroundColor": false,
  "hasClickThrough": true,
  "hasClippingMask": false,
  "horizontalRulerData": {
    "_class": "rulerData",
    "base": 0,
    "do_objectID": "C0BD3357-73EA-40E2-8924-E09F4899BECB",
    "guides": [
    ]
  },
  "includeBackgroundColorInExport": true,
  "includeBackgroundColorInInstance": true,
  "includeInCloudUpload": true,
  "isFixedToViewport": false,
  "isFlippedHorizontal": false,
  "isFlippedVertical": false,
  "isFlowHome": false,
  "isLocked": false,
  "isVisible": true,
  "layerListExpandedType": 0,
  "layers": [
    {
      "class": "rectangle",
      "id": "2DFA691D-42AF-4189-9DCB-044BBA95BADE"
    },
    {
      "class": "symbolInstance",
      "id": "41483EE0-1C66-43D1-906C-7830C6E8BC88"
    },
    {
      "class": "shapeGroup",
      "id": "965C2B5D-79F5-4296-A8FB-F8C22975AA07"
    },
    {
      "class": "text",
      "id": "3D62850C-BC10-4165-8532-131A85780CBA"
    }
  ],
  "name": "Elements/Tag/wClose",
  "nameIsFixed": true,
  "resizesContent": true,
  "resizingConstraint": 63,
  "resizingType": 0,
  "rotation": 0,
  "shouldBreakMaskChain": true,
  "style": {
    "_class": "style",
    "do_objectID": "7565B604-EAAE-40D8-A79E-BA4D96CE144D",
    "endMarkerType": 0,
    "miterLimit": 10,
    "startMarkerType": 0,
    "windingRule": 1
  },
  "symbolID": "12AD6346-378A-41F8-8909-04FD08C44F7F",
  "verticalRulerData": {
    "_class": "rulerData",
    "base": 0,
    "do_objectID": "AFD1EFBB-3416-435B-B337-17DAF134E0CD",
    "guides": [
    ]
  }
}