{
  "_class": "symbolInstance",
  "booleanOperation": -1,
  "do_objectID": "667B06E1-8C0E-47EC-BAF9-382D06D05265",
  "exportOptions": {
    "_class": "exportOptions",
    "do_objectID": "9EF68B17-6327-48CD-B722-E6D0D72DB6AC",
    "exportFormats": [
    ],
    "includedLayerIds": [
    ],
    "layerOptions": 0,
    "shouldTrim": false
  },
  "frame": {
    "_class": "rect",
    "constrainProportions": false,
    "do_objectID": "CCF2AEB5-A2E1-4E37-B22D-A0082AE6EC60",
    "height": 114,
    "width": 375,
    "x": 0,
    "y": 356
  },
  "horizontalSpacing": 0,
  "isFixedToViewport": false,
  "isFlippedHorizontal": false,
  "isFlippedVertical": false,
  "isLocked": false,
  "isVisible": true,
  "layerListExpandedType": 0,
  "name": "Views/MediaItem/Product/Sale Copy 2",
  "nameIsFixed": false,
  "overrideValues": [
    {
      "_class": "overrideValue",
      "do_objectID": "98C646FA-05E0-40BB-903A-EE29F096CA9D",
      "overrideName": "57989ABA-D909-48DA-8E19-2F2174F7D983_stringValue",
      "value": "x 1"
    },
    {
      "_class": "overrideValue",
      "do_objectID": "835C784E-4FB7-4DC4-9E03-DF66BA2C2954",
      "overrideName": "79CDD2A8-EEB3-4E40-9174-465C7604A7E2_image",
      "value": {
        "_class": "MSJSONFileReference",
        "_ref": "images/313e2dc7ab4a3936df1346de96a7b801bf1b8e95.png",
        "_ref_class": "MSImageData"
      }
    },
    {
      "_class": "overrideValue",
      "do_objectID": "C4BD8CED-8BE3-4B3D-A941-2F2FC9549DCE",
      "overrideName": "3E4755EF-55CE-4173-9BF4-F91A7344FC03_stringValue",
      "value": "Lucas Papaw"
    },
    {
      "_class": "overrideValue",
      "do_objectID": "C02669A5-6190-4283-9EB1-817674D9BCA7",
      "overrideName": "391CE578-3243-4689-AD86-D8CEF14A81F3_stringValue",
      "value": "Soothing Ointment (25g)"
    },
    {
      "_class": "overrideValue",
      "do_objectID": "5410A7BB-DDEC-42F4-AF1B-370A1BADC86E",
      "overrideName": "568F1881-3D90-40A7-A456-D0CC6255FF5D_stringValue",
      "value": "P500.00"
    },
    {
      "_class": "overrideValue",
      "do_objectID": "DD7DC987-842D-404A-A201-8E57FC18C2E5",
      "overrideName": "24061B94-D0E8-4BF1-995B-0FC67FC8EF54_stringValue",
      "value": "P500.00"
    }
  ],
  "resizingConstraint": 63,
  "resizingType": 0,
  "rotation": 0,
  "scale": 1,
  "shouldBreakMaskChain": false,
  "style": {
    "_class": "style",
    "do_objectID": "FC3BF377-9FC6-4355-8C1C-018D4D743565",
    "endMarkerType": 0,
    "miterLimit": 10,
    "startMarkerType": 0,
    "windingRule": 1
  },
  "symbolID": "BEC8258B-A497-4414-A7A3-23D2128B8FAC",
  "verticalSpacing": 0
}