{
  "_class": "symbolInstance",
  "booleanOperation": -1,
  "clippingMaskMode": 0,
  "do_objectID": "A60CF904-4763-4A2F-AAAE-7AFD535B71C4",
  "exportOptions": {
    "_class": "exportOptions",
    "do_objectID": "4C61CA90-F2A1-44FD-944E-F61274B7062E",
    "exportFormats": [
    ],
    "includedLayerIds": [
    ],
    "layerOptions": 0,
    "shouldTrim": false
  },
  "frame": {
    "_class": "rect",
    "constrainProportions": false,
    "do_objectID": "5323430D-BEB5-4778-BB22-608C25EA1782",
    "height": 53,
    "width": 3,
    "x": 6,
    "y": 2
  },
  "hasClippingMask": false,
  "horizontalSpacing": 0,
  "isFixedToViewport": false,
  "isFlippedHorizontal": false,
  "isFlippedVertical": false,
  "isLocked": false,
  "isVisible": true,
  "layerListExpandedType": 0,
  "name": "Uni/YSolidLine",
  "nameIsFixed": false,
  "overrideValues": [
  ],
  "resizingConstraint": 63,
  "resizingType": 0,
  "rotation": 0,
  "scale": 1,
  "shouldBreakMaskChain": false,
  "style": {
    "_class": "style",
    "do_objectID": "050A1885-5152-4DC7-9372-9EC862328C10",
    "endMarkerType": 0,
    "miterLimit": 10,
    "startMarkerType": 0,
    "windingRule": 1
  },
  "symbolID": "06E7B44C-EF8A-4974-BB2F-D454ADEA5A4B",
  "verticalSpacing": 0
}