{
  "_class": "group",
  "booleanOperation": -1,
  "do_objectID": "A2F3C6C0-7419-49BC-B0EC-F806747A02E5",
  "exportOptions": {
    "_class": "exportOptions",
    "exportFormats": [
    ],
    "includedLayerIds": [
    ],
    "layerOptions": 0,
    "shouldTrim": false
  },
  "frame": {
    "_class": "rect",
    "constrainProportions": true,
    "height": 29,
    "width": 19,
    "x": 14.6969620481436,
    "y": 2.729843707776823
  },
  "hasClickThrough": false,
  "isFixedToViewport": false,
  "isFlippedHorizontal": false,
  "isFlippedVertical": false,
  "isLocked": false,
  "isVisible": true,
  "layerListExpandedType": 0,
  "layers": [
    {
      "class": "shapeGroup",
      "id": "90EA57BB-E8A9-4DA7-99BB-1398FC368BBC"
    },
    {
      "class": "shapeGroup",
      "id": "B6D5FD9C-615C-411E-917A-957DDFBA2D22"
    }
  ],
  "name": "Group",
  "nameIsFixed": false,
  "resizingConstraint": 45,
  "resizingType": 0,
  "rotation": 43,
  "shouldBreakMaskChain": false,
  "style": {
    "_class": "style",
    "endMarkerType": 0,
    "miterLimit": 10,
    "startMarkerType": 0,
    "windingRule": 1
  }
}