{
  "_class": "symbolInstance",
  "booleanOperation": -1,
  "do_objectID": "F6DD7B87-8670-4EF5-BBC1-9B66A7E1669F",
  "exportOptions": {
    "_class": "exportOptions",
    "do_objectID": "555F16F6-A9D3-4627-9E85-A01B4EF49E30",
    "exportFormats": [
    ],
    "includedLayerIds": [
    ],
    "layerOptions": 0,
    "shouldTrim": false
  },
  "frame": {
    "_class": "rect",
    "constrainProportions": false,
    "do_objectID": "1303F928-EDAC-4E90-95AB-FD528137DE9B",
    "height": 15,
    "width": 16,
    "x": 0,
    "y": 26
  },
  "horizontalSpacing": 0,
  "isFixedToViewport": false,
  "isFlippedHorizontal": false,
  "isFlippedVertical": false,
  "isLocked": false,
  "isVisible": true,
  "layerListExpandedType": 0,
  "name": "Uni/UnitBox Copy",
  "nameIsFixed": false,
  "overrideValues": [
    {
      "_class": "overrideValue",
      "do_objectID": "38B016B0-8BA8-49A5-82F0-E75489CD7489",
      "overrideName": "AEA4C197-2DF5-4FE7-BEEE-47042A373812_stringValue",
      "value": "8"
    }
  ],
  "resizingConstraint": 63,
  "resizingType": 0,
  "rotation": 0,
  "scale": 1,
  "shouldBreakMaskChain": false,
  "style": {
    "_class": "style",
    "do_objectID": "014BDAE9-DD56-4D87-AF62-A320CAAD2FFF",
    "endMarkerType": 0,
    "miterLimit": 10,
    "startMarkerType": 0,
    "windingRule": 1
  },
  "symbolID": "38CF320E-A940-40CB-A98F-AF189FF48EB7",
  "verticalSpacing": 0
}