{
  "_class": "group",
  "booleanOperation": -1,
  "clippingMaskMode": 0,
  "do_objectID": "D0608EF3-B5DF-4BCD-BFDC-C2239D762D96",
  "exportOptions": {
    "_class": "exportOptions",
    "do_objectID": "6DA89042-AB63-4071-BA93-7145F4054EA3",
    "exportFormats": [
    ],
    "includedLayerIds": [
    ],
    "layerOptions": 0,
    "shouldTrim": false
  },
  "frame": {
    "_class": "rect",
    "constrainProportions": false,
    "do_objectID": "F8D7FAC1-008C-4786-A67A-A0944D83202B",
    "height": 48,
    "width": 344,
    "x": 8,
    "y": 8
  },
  "hasClickThrough": false,
  "hasClippingMask": false,
  "isFixedToViewport": false,
  "isFlippedHorizontal": false,
  "isFlippedVertical": false,
  "isLocked": false,
  "isVisible": true,
  "layerListExpandedType": 0,
  "layers": [
    {
      "class": "rectangle",
      "id": "73BD5BCA-3242-42F5-9418-DC28BEC81C2E"
    },
    {
      "class": "text",
      "id": "A630EAD1-C66B-4A9F-B7DC-73FD3B9D80A5"
    }
  ],
  "name": "Snackbar",
  "nameIsFixed": true,
  "resizingConstraint": 63,
  "resizingType": 0,
  "rotation": 0,
  "shouldBreakMaskChain": false,
  "style": {
    "_class": "style",
    "do_objectID": "B84E425B-14DB-484C-B07B-D4FD3810496A",
    "endMarkerType": 0,
    "miterLimit": 10,
    "startMarkerType": 0,
    "windingRule": 1
  }
}