{
  "_class": "symbolInstance",
  "booleanOperation": -1,
  "clippingMaskMode": 0,
  "do_objectID": "C5893E20-F2BD-406D-A748-EBFD9F1E995B",
  "exportOptions": {
    "_class": "exportOptions",
    "do_objectID": "2C77C849-E6CD-4890-A4C3-9C89602AF482",
    "exportFormats": [
    ],
    "includedLayerIds": [
    ],
    "layerOptions": 0,
    "shouldTrim": false
  },
  "frame": {
    "_class": "rect",
    "constrainProportions": false,
    "do_objectID": "279F4D11-4688-4212-8355-ACEDAAA1EAB1",
    "height": 45,
    "width": 375,
    "x": 24,
    "y": 30
  },
  "hasClippingMask": false,
  "horizontalSpacing": 0,
  "isFixedToViewport": false,
  "isFlippedHorizontal": false,
  "isFlippedVertical": false,
  "isLocked": false,
  "isVisible": true,
  "layerListExpandedType": 0,
  "name": "Navigation/Default",
  "nameIsFixed": true,
  "overrideValues": [
  ],
  "resizingConstraint": 63,
  "resizingType": 0,
  "rotation": 0,
  "scale": 1,
  "shouldBreakMaskChain": false,
  "style": {
    "_class": "style",
    "do_objectID": "39589B6A-86FE-4778-BF90-584DE1775A69",
    "endMarkerType": 0,
    "miterLimit": 10,
    "startMarkerType": 0,
    "windingRule": 1
  },
  "symbolID": "BB740BCB-967E-496A-8710-72DC6CC30F41",
  "verticalSpacing": 0
}