{
  "_class": "symbolInstance",
  "booleanOperation": -1,
  "clippingMaskMode": 0,
  "do_objectID": "5EC3A173-FA8E-4DFB-BB22-5AE6193F49E5",
  "exportOptions": {
    "_class": "exportOptions",
    "do_objectID": "20308510-0734-4841-9757-EC6FDAF62C14",
    "exportFormats": [
    ],
    "includedLayerIds": [
    ],
    "layerOptions": 0,
    "shouldTrim": false
  },
  "frame": {
    "_class": "rect",
    "constrainProportions": false,
    "do_objectID": "5F983EA8-A3EA-4942-8FBE-23E255DCEA86",
    "height": 45,
    "width": 375,
    "x": 0,
    "y": 20
  },
  "hasClippingMask": false,
  "horizontalSpacing": 0,
  "isFixedToViewport": false,
  "isFlippedHorizontal": false,
  "isFlippedVertical": false,
  "isLocked": false,
  "isVisible": true,
  "layerListExpandedType": 0,
  "name": "Navigation/Default",
  "nameIsFixed": true,
  "overrideValues": [
    {
      "_class": "overrideValue",
      "do_objectID": "AF506494-9CDA-4342-BBCD-7016B6C51AE5",
      "overrideName": "6B66D73C-74B0-4698-8F86-968054027824_stringValue",
      "value": "Account Settings"
    }
  ],
  "resizingConstraint": 63,
  "resizingType": 0,
  "rotation": 0,
  "scale": 1,
  "shouldBreakMaskChain": false,
  "style": {
    "_class": "style",
    "do_objectID": "C19AEAEC-79A6-457A-A7FF-287C2E4B4E14",
    "endMarkerType": 0,
    "miterLimit": 10,
    "startMarkerType": 0,
    "windingRule": 1
  },
  "symbolID": "BB740BCB-967E-496A-8710-72DC6CC30F41",
  "verticalSpacing": 0
}