{
  "_class": "text",
  "attributedString": {
    "_class": "attributedString",
    "attributes": [
      {
        "_class": "stringAttribute",
        "attributes": {
          "MSAttributedStringColorAttribute": {
            "_class": "color",
            "alpha": 1,
            "blue": 1,
            "green": 1,
            "red": 1
          },
          "MSAttributedStringFontAttribute": {
            "_class": "fontDescriptor",
            "attributes": {
              "name": "SFUIText-Regular",
              "size": 12
            }
          },
          "kerning": 0,
          "paragraphStyle": {
            "_class": "paragraphStyle",
            "alignment": 0,
            "allowsDefaultTighteningForTruncation": 0
          },
          "textStyleVerticalAlignmentKey": 0
        },
        "length": 12,
        "location": 0
      }
    ],
    "string": "$darker-gray"
  },
  "automaticallyDrawOnUnderlyingPath": false,
  "booleanOperation": -1,
  "do_objectID": "4375AC9B-73DE-47CD-A929-2ADDC3751B90",
  "dontSynchroniseWithSymbol": false,
  "exportOptions": {
    "_class": "exportOptions",
    "do_objectID": "17BDCB51-EE1C-464A-9D2F-34B6F52FF48E",
    "exportFormats": [
    ],
    "includedLayerIds": [
    ],
    "layerOptions": 0,
    "shouldTrim": false
  },
  "frame": {
    "_class": "rect",
    "constrainProportions": false,
    "do_objectID": "D7546765-6E99-4104-B09F-23FBDC67B758",
    "height": 14,
    "width": 75,
    "x": 15,
    "y": 79
  },
  "glyphBounds": "{{0, 1}, {75, 13}}",
  "isFixedToViewport": false,
  "isFlippedHorizontal": false,
  "isFlippedVertical": false,
  "isLocked": false,
  "isVisible": true,
  "layerListExpandedType": 0,
  "lineSpacingBehaviour": 2,
  "name": "$darker-gray",
  "nameIsFixed": false,
  "resizingConstraint": 47,
  "resizingType": 0,
  "rotation": 0,
  "shouldBreakMaskChain": false,
  "style": {
    "_class": "style",
    "do_objectID": "A9EB6FFB-3423-4CD1-9544-2E3FA6DF6F07",
    "endMarkerType": 0,
    "miterLimit": 10,
    "startMarkerType": 0,
    "textStyle": {
      "_class": "textStyle",
      "do_objectID": "ABF85463-0DBF-4C8C-976C-40F6A87D630A",
      "encodedAttributes": {
        "MSAttributedStringColorAttribute": {
          "_class": "color",
          "alpha": 1,
          "blue": 1,
          "green": 1,
          "red": 1
        },
        "MSAttributedStringFontAttribute": {
          "_class": "fontDescriptor",
          "attributes": {
            "name": "SFUIText-Regular",
            "size": 12
          }
        },
        "kerning": 0,
        "paragraphStyle": {
          "_class": "paragraphStyle",
          "alignment": 0,
          "allowsDefaultTighteningForTruncation": 0
        },
        "textStyleVerticalAlignmentKey": 0
      },
      "verticalAlignment": 0
    },
    "windingRule": 1
  },
  "textBehaviour": 0
}