{
  "_class": "group",
  "booleanOperation": -1,
  "clippingMaskMode": 0,
  "do_objectID": "7A2536F1-082A-44EE-80E6-351DB1497FCA",
  "exportOptions": {
    "_class": "exportOptions",
    "do_objectID": "C309552F-0640-499E-A23A-EFC94C7A6058",
    "exportFormats": [
    ],
    "includedLayerIds": [
    ],
    "layerOptions": 0,
    "shouldTrim": false
  },
  "frame": {
    "_class": "rect",
    "constrainProportions": false,
    "do_objectID": "EA5E26E2-123D-4809-AF4A-596BDA67F635",
    "height": 33,
    "width": 16,
    "x": 117,
    "y": 376
  },
  "hasClickThrough": false,
  "hasClippingMask": false,
  "isFixedToViewport": false,
  "isFlippedHorizontal": false,
  "isFlippedVertical": false,
  "isLocked": false,
  "isVisible": true,
  "layerListExpandedType": 2,
  "layers": [
    {
      "class": "symbolInstance",
      "id": "FE0E657E-8ECD-4AE4-9CE1-444F4B2A47C8"
    },
    {
      "class": "symbolInstance",
      "id": "F5F9F1CB-18BE-426B-8866-58AD5A2E9A97"
    },
    {
      "class": "symbolInstance",
      "id": "0A4E5562-316C-4A23-A596-23DF40F64D2C"
    },
    {
      "class": "symbolInstance",
      "id": "F72C17C5-E585-430E-9F4F-FB4BCC7A638B"
    }
  ],
  "name": "Group Copy 7",
  "nameIsFixed": false,
  "resizingConstraint": 63,
  "resizingType": 0,
  "rotation": 0,
  "shouldBreakMaskChain": false,
  "style": {
    "_class": "style",
    "do_objectID": "95FF3813-0B5C-4495-9DDC-E1D42CA33393",
    "endMarkerType": 0,
    "miterLimit": 10,
    "startMarkerType": 0,
    "windingRule": 1
  }
}