{
  "_class": "artboard",
  "backgroundColor": {
    "_class": "color",
    "alpha": 1,
    "blue": 1,
    "green": 1,
    "red": 1
  },
  "booleanOperation": -1,
  "do_objectID": "A4D9F0A9-E1D8-4D02-81DD-EBC8A297F453",
  "exportOptions": {
    "_class": "exportOptions",
    "exportFormats": [
    ],
    "includedLayerIds": [
    ],
    "layerOptions": 0,
    "shouldTrim": false
  },
  "frame": {
    "_class": "rect",
    "constrainProportions": false,
    "height": 764,
    "width": 593,
    "x": -442,
    "y": 379
  },
  "hasBackgroundColor": false,
  "hasClickThrough": true,
  "horizontalRulerData": {
    "_class": "rulerData",
    "base": 0,
    "guides": [
    ]
  },
  "includeBackgroundColorInExport": true,
  "includeInCloudUpload": true,
  "isFixedToViewport": false,
  "isFlippedHorizontal": false,
  "isFlippedVertical": false,
  "isFlowHome": false,
  "isLocked": false,
  "isVisible": true,
  "layerListExpandedType": 2,
  "layers": [
    {
      "class": "group",
      "id": "351B742D-ABE4-4E28-AED3-41CD58BC6A58"
    },
    {
      "class": "group",
      "id": "89A811EC-7177-409A-B1C5-D7F68D075FBB"
    },
    {
      "class": "group",
      "id": "DF6662D1-E2AB-4118-8689-09F0D1B6C3D7"
    },
    {
      "class": "group",
      "id": "628A98EA-0F66-464C-8ACB-B0E37E5A4FF2"
    },
    {
      "class": "group",
      "id": "0359D801-97A4-4E5A-9DC7-C8F54B9A8625"
    },
    {
      "class": "group",
      "id": "1B19AE44-1538-45F2-BE5C-F8EE1D88A668"
    },
    {
      "class": "group",
      "id": "A478707D-B6F6-4DE2-9488-A8780634BC22"
    },
    {
      "class": "group",
      "id": "36305907-1290-4062-9479-8242F240FA2B"
    },
    {
      "class": "group",
      "id": "E736C34D-79A5-46DB-BBA6-6F1E7DD8D7B3"
    },
    {
      "class": "group",
      "id": "05482A3B-6471-48BC-A9DF-18E36631E3EB"
    },
    {
      "class": "symbolInstance",
      "id": "941920A1-FE91-4393-BE15-BC382C33E56B"
    }
  ],
  "name": "Product",
  "nameIsFixed": true,
  "resizesContent": false,
  "resizingConstraint": 63,
  "resizingType": 0,
  "rotation": 0,
  "shouldBreakMaskChain": true,
  "style": {
    "_class": "style",
    "endMarkerType": 0,
    "miterLimit": 10,
    "startMarkerType": 0,
    "windingRule": 1
  },
  "verticalRulerData": {
    "_class": "rulerData",
    "base": 0,
    "guides": [
    ]
  }
}