{
  "_class": "symbolInstance",
  "booleanOperation": -1,
  "do_objectID": "04812D25-916B-4CE7-AF75-0A8E012C05E7",
  "exportOptions": {
    "_class": "exportOptions",
    "do_objectID": "33978384-BC4F-411B-BC56-176722A1DCD6",
    "exportFormats": [
    ],
    "includedLayerIds": [
    ],
    "layerOptions": 0,
    "shouldTrim": false
  },
  "frame": {
    "_class": "rect",
    "constrainProportions": false,
    "do_objectID": "964527DE-D5EB-41B4-A935-D78B5780A160",
    "height": 19,
    "width": 1,
    "x": 12,
    "y": 0
  },
  "horizontalSpacing": 0,
  "isFixedToViewport": false,
  "isFlippedHorizontal": false,
  "isFlippedVertical": false,
  "isLocked": false,
  "isVisible": true,
  "layerListExpandedType": 0,
  "name": "Uni/YDashedLine",
  "nameIsFixed": false,
  "overrideValues": [
  ],
  "resizingConstraint": 63,
  "resizingType": 0,
  "rotation": 0,
  "scale": 1,
  "shouldBreakMaskChain": false,
  "style": {
    "_class": "style",
    "do_objectID": "8526B2EE-8DD8-4C8F-8ECF-58350DF088EE",
    "endMarkerType": 0,
    "miterLimit": 10,
    "startMarkerType": 0,
    "windingRule": 1
  },
  "symbolID": "4E753A36-6896-4DDD-8E26-7A9F9D794B40",
  "verticalSpacing": 0
}