{
  "_class": "group",
  "booleanOperation": -1,
  "do_objectID": "430621A5-FDB8-402A-97CF-3FAE132B874E",
  "exportOptions": {
    "_class": "exportOptions",
    "do_objectID": "2D68BAD4-1781-4234-849D-77C0E98584A9",
    "exportFormats": [
    ],
    "includedLayerIds": [
    ],
    "layerOptions": 0,
    "shouldTrim": false
  },
  "frame": {
    "_class": "rect",
    "constrainProportions": false,
    "do_objectID": "F9C74288-E956-480E-BCBA-41D78D3B1528",
    "height": 79,
    "width": 16,
    "x": 103,
    "y": 265
  },
  "hasClickThrough": false,
  "isFixedToViewport": false,
  "isFlippedHorizontal": false,
  "isFlippedVertical": false,
  "isLocked": false,
  "isVisible": true,
  "layerListExpandedType": 0,
  "layers": [
    {
      "class": "symbolInstance",
      "id": "66730DBE-AAD2-432D-AE1D-413877842065"
    },
    {
      "class": "shapeGroup",
      "id": "4BC4F524-C8D2-46CF-AA43-E7B185290FF7"
    },
    {
      "class": "symbolInstance",
      "id": "2135ECBD-912F-48AF-8D5B-F20F88882A44"
    },
    {
      "class": "symbolInstance",
      "id": "18D942C2-7319-4E2B-9727-73B77400FAB6"
    }
  ],
  "name": "Group 2 Copy 2",
  "nameIsFixed": false,
  "resizingConstraint": 63,
  "resizingType": 0,
  "rotation": 0,
  "shouldBreakMaskChain": false,
  "style": {
    "_class": "style",
    "do_objectID": "62007FBA-A524-4F6C-8AA8-7B1AB08A4A8B",
    "endMarkerType": 0,
    "miterLimit": 10,
    "startMarkerType": 0,
    "windingRule": 1
  }
}